<?xml version="1.0" encoding="UTF-8"?>
<DUT_AutoMorpher>
	<Section ID="7" SPID="40" IsDeformed="F" IsClosed="T">
		<EmbPoint ID="0" X="217.29153400000001" Y="30" Z="40" />
		<EmbPoint ID="1" X="217.29153400000001" Y="27.600000000000001" Z="40" />
		<EmbPoint ID="2" X="217.29153400000001" Y="25.199999999999999" Z="40" />
		<EmbPoint ID="3" X="217.29153400000001" Y="22.800000000000001" Z="40" />
		<EmbPoint ID="4" X="217.29153400000001" Y="20.399999999999999" Z="40" />
		<EmbPoint ID="5" X="217.29153400000001" Y="18" Z="40" />
		<EmbPoint ID="6" X="217.29153400000001" Y="15.600000000000001" Z="40" />
		<EmbPoint ID="7" X="217.29153400000001" Y="13.199999999999999" Z="40" />
		<EmbPoint ID="8" X="217.29153400000001" Y="10.800000000000001" Z="40" />
		<EmbPoint ID="9" X="217.29153400000001" Y="8.4000000000000021" Z="40" />
		<EmbPoint ID="10" X="217.29153400000001" Y="6" Z="40" />
		<EmbPoint ID="11" X="217.29153400000001" Y="3.6000000000000014" Z="40" />
		<EmbPoint ID="12" X="217.29153400000001" Y="1.2000000000000028" Z="40" />
		<EmbPoint ID="13" X="217.29153400000001" Y="-1.1999999999999993" Z="40" />
		<EmbPoint ID="14" X="217.29153400000001" Y="-3.6000000000000014" Z="40" />
		<EmbPoint ID="15" X="217.29153400000001" Y="-6" Z="40" />
		<EmbPoint ID="16" X="217.29153400000001" Y="-8.3999999999999986" Z="40" />
		<EmbPoint ID="17" X="217.29153400000001" Y="-10.799999999999997" Z="40" />
		<EmbPoint ID="18" X="217.29153400000001" Y="-13.199999999999996" Z="40" />
		<EmbPoint ID="19" X="217.29153400000001" Y="-15.600000000000001" Z="40" />
		<EmbPoint ID="20" X="217.29153400000001" Y="-18" Z="40" />
		<EmbPoint ID="21" X="217.29153400000001" Y="-20.399999999999999" Z="40" />
		<EmbPoint ID="22" X="217.29153400000001" Y="-22.799999999999997" Z="40" />
		<EmbPoint ID="23" X="217.29153400000001" Y="-25.199999999999996" Z="40" />
		<EmbPoint ID="24" X="217.29153400000001" Y="-27.599999999999994" Z="40" />
		<EmbPoint ID="25" X="217.29153400000001" Y="-30" Z="40" />
		<EmbPoint ID="26" X="217.29153400000001" Y="-30" Z="36.799999999999997" />
		<EmbPoint ID="27" X="217.29153400000001" Y="-30" Z="33.600000000000001" />
		<EmbPoint ID="28" X="217.29153400000001" Y="-30" Z="30.399999999999999" />
		<EmbPoint ID="29" X="217.29153400000001" Y="-30" Z="27.199999999999999" />
		<EmbPoint ID="30" X="217.29153400000001" Y="-30" Z="24" />
		<EmbPoint ID="31" X="217.29153400000001" Y="-30" Z="20.799999999999997" />
		<EmbPoint ID="32" X="217.29153400000001" Y="-30" Z="17.599999999999998" />
		<EmbPoint ID="33" X="217.29153400000001" Y="-30" Z="14.399999999999999" />
		<EmbPoint ID="34" X="217.29153400000001" Y="-30" Z="11.199999999999999" />
		<EmbPoint ID="35" X="217.29153400000001" Y="-30" Z="8" />
		<EmbPoint ID="36" X="217.29153400000001" Y="-30" Z="4.7999999999999972" />
		<EmbPoint ID="37" X="217.29153400000001" Y="-30" Z="1.5999999999999943" />
		<EmbPoint ID="38" X="217.29153400000001" Y="-30" Z="-1.6000000000000014" />
		<EmbPoint ID="39" X="217.29153400000001" Y="-30" Z="-4.8000000000000043" />
		<EmbPoint ID="40" X="217.29153400000001" Y="-30" Z="-8" />
		<EmbPoint ID="41" X="217.29153400000001" Y="-30" Z="-11.200000000000003" />
		<EmbPoint ID="42" X="217.29153400000001" Y="-30" Z="-14.400000000000006" />
		<EmbPoint ID="43" X="217.29153400000001" Y="-30" Z="-17.600000000000001" />
		<EmbPoint ID="44" X="217.29153400000001" Y="-30" Z="-20.800000000000004" />
		<EmbPoint ID="45" X="217.29153400000001" Y="-30" Z="-24" />
		<EmbPoint ID="46" X="217.29153400000001" Y="-30" Z="-27.200000000000003" />
		<EmbPoint ID="47" X="217.29153400000001" Y="-30" Z="-30.400000000000006" />
		<EmbPoint ID="48" X="217.29153400000001" Y="-30" Z="-33.600000000000009" />
		<EmbPoint ID="49" X="217.29153400000001" Y="-30" Z="-36.800000000000011" />
		<EmbPoint ID="50" X="217.29153400000001" Y="-30" Z="-40" />
		<EmbPoint ID="51" X="217.29153400000001" Y="-27.600000000000001" Z="-40" />
		<EmbPoint ID="52" X="217.29153400000001" Y="-25.199999999999999" Z="-40" />
		<EmbPoint ID="53" X="217.29153400000001" Y="-22.800000000000001" Z="-40" />
		<EmbPoint ID="54" X="217.29153400000001" Y="-20.399999999999999" Z="-40" />
		<EmbPoint ID="55" X="217.29153400000001" Y="-18" Z="-40" />
		<EmbPoint ID="56" X="217.29153400000001" Y="-15.600000000000001" Z="-40" />
		<EmbPoint ID="57" X="217.29153400000001" Y="-13.199999999999999" Z="-40" />
		<EmbPoint ID="58" X="217.29153400000001" Y="-10.800000000000001" Z="-40" />
		<EmbPoint ID="59" X="217.29153400000001" Y="-8.4000000000000021" Z="-40" />
		<EmbPoint ID="60" X="217.29153400000001" Y="-6" Z="-40" />
		<EmbPoint ID="61" X="217.29153400000001" Y="-3.6000000000000014" Z="-40" />
		<EmbPoint ID="62" X="217.29153400000001" Y="-1.2000000000000028" Z="-40" />
		<EmbPoint ID="63" X="217.29153400000001" Y="1.1999999999999993" Z="-40" />
		<EmbPoint ID="64" X="217.29153400000001" Y="3.6000000000000014" Z="-40" />
		<EmbPoint ID="65" X="217.29153400000001" Y="6" Z="-40" />
		<EmbPoint ID="66" X="217.29153400000001" Y="8.3999999999999986" Z="-40" />
		<EmbPoint ID="67" X="217.29153400000001" Y="10.799999999999997" Z="-40" />
		<EmbPoint ID="68" X="217.29153400000001" Y="13.199999999999996" Z="-40" />
		<EmbPoint ID="69" X="217.29153400000001" Y="15.600000000000001" Z="-40" />
		<EmbPoint ID="70" X="217.29153400000001" Y="18" Z="-40" />
		<EmbPoint ID="71" X="217.29153400000001" Y="20.399999999999999" Z="-40" />
		<EmbPoint ID="72" X="217.29153400000001" Y="22.799999999999997" Z="-40" />
		<EmbPoint ID="73" X="217.29153400000001" Y="25.199999999999996" Z="-40" />
		<EmbPoint ID="74" X="217.29153400000001" Y="27.599999999999994" Z="-40" />
		<EmbPoint ID="75" X="217.29153400000001" Y="30" Z="-40" />
		<EmbPoint ID="76" X="217.29153400000001" Y="30" Z="-36.799999999999997" />
		<EmbPoint ID="77" X="217.29153400000001" Y="30" Z="-33.600000000000001" />
		<EmbPoint ID="78" X="217.29153400000001" Y="30" Z="-30.399999999999999" />
		<EmbPoint ID="79" X="217.29153400000001" Y="30" Z="-27.199999999999999" />
		<EmbPoint ID="80" X="217.29153400000001" Y="30" Z="-24" />
		<EmbPoint ID="81" X="217.29153400000001" Y="30" Z="-20.799999999999997" />
		<EmbPoint ID="82" X="217.29153400000001" Y="30" Z="-17.599999999999998" />
		<EmbPoint ID="83" X="217.29153400000001" Y="30" Z="-14.399999999999999" />
		<EmbPoint ID="84" X="217.29153400000001" Y="30" Z="-11.199999999999999" />
		<EmbPoint ID="85" X="217.29153400000001" Y="30" Z="-8" />
		<EmbPoint ID="86" X="217.29153400000001" Y="30" Z="-4.7999999999999972" />
		<EmbPoint ID="87" X="217.29153400000001" Y="30" Z="-1.5999999999999943" />
		<EmbPoint ID="88" X="217.29153400000001" Y="30" Z="1.6000000000000014" />
		<EmbPoint ID="89" X="217.29153400000001" Y="30" Z="4.8000000000000043" />
		<EmbPoint ID="90" X="217.29153400000001" Y="30" Z="8" />
		<EmbPoint ID="91" X="217.29153400000001" Y="30" Z="11.200000000000003" />
		<EmbPoint ID="92" X="217.29153400000001" Y="30" Z="14.400000000000006" />
		<EmbPoint ID="93" X="217.29153400000001" Y="30" Z="17.600000000000001" />
		<EmbPoint ID="94" X="217.29153400000001" Y="30" Z="20.800000000000004" />
		<EmbPoint ID="95" X="217.29153400000001" Y="30" Z="24" />
		<EmbPoint ID="96" X="217.29153400000001" Y="30" Z="27.200000000000003" />
		<EmbPoint ID="97" X="217.29153400000001" Y="30" Z="30.400000000000006" />
		<EmbPoint ID="98" X="217.29153400000001" Y="30" Z="33.600000000000009" />
		<EmbPoint ID="99" X="217.29153400000001" Y="30" Z="36.800000000000011" />
	</Section>
	<Section ID="8" SPID="45" IsDeformed="F" IsClosed="T">
		<EmbPoint ID="0" X="244.30178799999999" Y="30" Z="40" />
		<EmbPoint ID="1" X="244.30178799999999" Y="27.600000000000001" Z="40" />
		<EmbPoint ID="2" X="244.30178799999999" Y="25.199999999999999" Z="40" />
		<EmbPoint ID="3" X="244.30178799999999" Y="22.800000000000001" Z="40" />
		<EmbPoint ID="4" X="244.30178799999999" Y="20.399999999999999" Z="40" />
		<EmbPoint ID="5" X="244.30178799999999" Y="18" Z="40" />
		<EmbPoint ID="6" X="244.30178799999999" Y="15.600000000000001" Z="40" />
		<EmbPoint ID="7" X="244.30178799999999" Y="13.199999999999999" Z="40" />
		<EmbPoint ID="8" X="244.30178799999999" Y="10.800000000000001" Z="40" />
		<EmbPoint ID="9" X="244.30178799999999" Y="8.4000000000000021" Z="40" />
		<EmbPoint ID="10" X="244.30178799999999" Y="6" Z="40" />
		<EmbPoint ID="11" X="244.30178799999999" Y="3.6000000000000014" Z="40" />
		<EmbPoint ID="12" X="244.30178799999999" Y="1.2000000000000028" Z="40" />
		<EmbPoint ID="13" X="244.30178799999999" Y="-1.1999999999999993" Z="40" />
		<EmbPoint ID="14" X="244.30178799999999" Y="-3.6000000000000014" Z="40" />
		<EmbPoint ID="15" X="244.30178799999999" Y="-6" Z="40" />
		<EmbPoint ID="16" X="244.30178799999999" Y="-8.3999999999999986" Z="40" />
		<EmbPoint ID="17" X="244.30178799999999" Y="-10.799999999999997" Z="40" />
		<EmbPoint ID="18" X="244.30178799999999" Y="-13.199999999999996" Z="40" />
		<EmbPoint ID="19" X="244.30178799999999" Y="-15.600000000000001" Z="40" />
		<EmbPoint ID="20" X="244.30178799999999" Y="-18" Z="40" />
		<EmbPoint ID="21" X="244.30178799999999" Y="-20.399999999999999" Z="40" />
		<EmbPoint ID="22" X="244.30178799999999" Y="-22.799999999999997" Z="40" />
		<EmbPoint ID="23" X="244.30178799999999" Y="-25.199999999999996" Z="40" />
		<EmbPoint ID="24" X="244.30178799999999" Y="-27.599999999999994" Z="40" />
		<EmbPoint ID="25" X="244.30178799999999" Y="-30" Z="40" />
		<EmbPoint ID="26" X="244.30178799999999" Y="-30" Z="36.799999999999997" />
		<EmbPoint ID="27" X="244.30178799999999" Y="-30" Z="33.600000000000001" />
		<EmbPoint ID="28" X="244.30178799999999" Y="-30" Z="30.399999999999999" />
		<EmbPoint ID="29" X="244.30178799999999" Y="-30" Z="27.199999999999999" />
		<EmbPoint ID="30" X="244.30178799999999" Y="-30" Z="24" />
		<EmbPoint ID="31" X="244.30178799999999" Y="-30" Z="20.799999999999997" />
		<EmbPoint ID="32" X="244.30178799999999" Y="-30" Z="17.599999999999998" />
		<EmbPoint ID="33" X="244.30178799999999" Y="-30" Z="14.399999999999999" />
		<EmbPoint ID="34" X="244.30178799999999" Y="-30" Z="11.199999999999999" />
		<EmbPoint ID="35" X="244.30178799999999" Y="-30" Z="8" />
		<EmbPoint ID="36" X="244.30178799999999" Y="-30" Z="4.7999999999999972" />
		<EmbPoint ID="37" X="244.30178799999999" Y="-30" Z="1.5999999999999943" />
		<EmbPoint ID="38" X="244.30178799999999" Y="-30" Z="-1.6000000000000014" />
		<EmbPoint ID="39" X="244.30178799999999" Y="-30" Z="-4.8000000000000043" />
		<EmbPoint ID="40" X="244.30178799999999" Y="-30" Z="-8" />
		<EmbPoint ID="41" X="244.30178799999999" Y="-30" Z="-11.200000000000003" />
		<EmbPoint ID="42" X="244.30178799999999" Y="-30" Z="-14.400000000000006" />
		<EmbPoint ID="43" X="244.30178799999999" Y="-30" Z="-17.600000000000001" />
		<EmbPoint ID="44" X="244.30178799999999" Y="-30" Z="-20.800000000000004" />
		<EmbPoint ID="45" X="244.30178799999999" Y="-30" Z="-24" />
		<EmbPoint ID="46" X="244.30178799999999" Y="-30" Z="-27.200000000000003" />
		<EmbPoint ID="47" X="244.30178799999999" Y="-30" Z="-30.400000000000006" />
		<EmbPoint ID="48" X="244.30178799999999" Y="-30" Z="-33.600000000000009" />
		<EmbPoint ID="49" X="244.30178799999999" Y="-30" Z="-36.800000000000011" />
		<EmbPoint ID="50" X="244.30178799999999" Y="-30" Z="-40" />
		<EmbPoint ID="51" X="244.30178799999999" Y="-27.600000000000001" Z="-40" />
		<EmbPoint ID="52" X="244.30178799999999" Y="-25.199999999999999" Z="-40" />
		<EmbPoint ID="53" X="244.30178799999999" Y="-22.800000000000001" Z="-40" />
		<EmbPoint ID="54" X="244.30178799999999" Y="-20.399999999999999" Z="-40" />
		<EmbPoint ID="55" X="244.30178799999999" Y="-18" Z="-40" />
		<EmbPoint ID="56" X="244.30178799999999" Y="-15.600000000000001" Z="-40" />
		<EmbPoint ID="57" X="244.30178799999999" Y="-13.199999999999999" Z="-40" />
		<EmbPoint ID="58" X="244.30178799999999" Y="-10.800000000000001" Z="-40" />
		<EmbPoint ID="59" X="244.30178799999999" Y="-8.4000000000000021" Z="-40" />
		<EmbPoint ID="60" X="244.30178799999999" Y="-6" Z="-40" />
		<EmbPoint ID="61" X="244.30178799999999" Y="-3.6000000000000014" Z="-40" />
		<EmbPoint ID="62" X="244.30178799999999" Y="-1.2000000000000028" Z="-40" />
		<EmbPoint ID="63" X="244.30178799999999" Y="1.1999999999999993" Z="-40" />
		<EmbPoint ID="64" X="244.30178799999999" Y="3.6000000000000014" Z="-40" />
		<EmbPoint ID="65" X="244.30178799999999" Y="6" Z="-40" />
		<EmbPoint ID="66" X="244.30178799999999" Y="8.3999999999999986" Z="-40" />
		<EmbPoint ID="67" X="244.30178799999999" Y="10.799999999999997" Z="-40" />
		<EmbPoint ID="68" X="244.30178799999999" Y="13.199999999999996" Z="-40" />
		<EmbPoint ID="69" X="244.30178799999999" Y="15.600000000000001" Z="-40" />
		<EmbPoint ID="70" X="244.30178799999999" Y="18" Z="-40" />
		<EmbPoint ID="71" X="244.30178799999999" Y="20.399999999999999" Z="-40" />
		<EmbPoint ID="72" X="244.30178799999999" Y="22.799999999999997" Z="-40" />
		<EmbPoint ID="73" X="244.30178799999999" Y="25.199999999999996" Z="-40" />
		<EmbPoint ID="74" X="244.30178799999999" Y="27.599999999999994" Z="-40" />
		<EmbPoint ID="75" X="244.30178799999999" Y="30" Z="-40" />
		<EmbPoint ID="76" X="244.30178799999999" Y="30" Z="-36.799999999999997" />
		<EmbPoint ID="77" X="244.30178799999999" Y="30" Z="-33.600000000000001" />
		<EmbPoint ID="78" X="244.30178799999999" Y="30" Z="-30.399999999999999" />
		<EmbPoint ID="79" X="244.30178799999999" Y="30" Z="-27.199999999999999" />
		<EmbPoint ID="80" X="244.30178799999999" Y="30" Z="-24" />
		<EmbPoint ID="81" X="244.30178799999999" Y="30" Z="-20.799999999999997" />
		<EmbPoint ID="82" X="244.30178799999999" Y="30" Z="-17.599999999999998" />
		<EmbPoint ID="83" X="244.30178799999999" Y="30" Z="-14.399999999999999" />
		<EmbPoint ID="84" X="244.30178799999999" Y="30" Z="-11.199999999999999" />
		<EmbPoint ID="85" X="244.30178799999999" Y="30" Z="-8" />
		<EmbPoint ID="86" X="244.30178799999999" Y="30" Z="-4.7999999999999972" />
		<EmbPoint ID="87" X="244.30178799999999" Y="30" Z="-1.5999999999999943" />
		<EmbPoint ID="88" X="244.30178799999999" Y="30" Z="1.6000000000000014" />
		<EmbPoint ID="89" X="244.30178799999999" Y="30" Z="4.8000000000000043" />
		<EmbPoint ID="90" X="244.30178799999999" Y="30" Z="8" />
		<EmbPoint ID="91" X="244.30178799999999" Y="30" Z="11.200000000000003" />
		<EmbPoint ID="92" X="244.30178799999999" Y="30" Z="14.400000000000006" />
		<EmbPoint ID="93" X="244.30178799999999" Y="30" Z="17.600000000000001" />
		<EmbPoint ID="94" X="244.30178799999999" Y="30" Z="20.800000000000004" />
		<EmbPoint ID="95" X="244.30178799999999" Y="30" Z="24" />
		<EmbPoint ID="96" X="244.30178799999999" Y="30" Z="27.200000000000003" />
		<EmbPoint ID="97" X="244.30178799999999" Y="30" Z="30.400000000000006" />
		<EmbPoint ID="98" X="244.30178799999999" Y="30" Z="33.600000000000009" />
		<EmbPoint ID="99" X="244.30178799999999" Y="30" Z="36.800000000000011" />
	</Section>
	<Section ID="9" SPID="50" IsDeformed="F" IsClosed="T">
		<EmbPoint ID="0" X="271.29177900000002" Y="30" Z="40" />
		<EmbPoint ID="1" X="271.29177900000002" Y="27.600000000000001" Z="40" />
		<EmbPoint ID="2" X="271.29177900000002" Y="25.199999999999999" Z="40" />
		<EmbPoint ID="3" X="271.29177900000002" Y="22.800000000000001" Z="40" />
		<EmbPoint ID="4" X="271.29177900000002" Y="20.399999999999999" Z="40" />
		<EmbPoint ID="5" X="271.29177900000002" Y="18" Z="40" />
		<EmbPoint ID="6" X="271.29177900000002" Y="15.600000000000001" Z="40" />
		<EmbPoint ID="7" X="271.29177900000002" Y="13.199999999999999" Z="40" />
		<EmbPoint ID="8" X="271.29177900000002" Y="10.800000000000001" Z="40" />
		<EmbPoint ID="9" X="271.29177900000002" Y="8.4000000000000021" Z="40" />
		<EmbPoint ID="10" X="271.29177900000002" Y="6" Z="40" />
		<EmbPoint ID="11" X="271.29177900000002" Y="3.6000000000000014" Z="40" />
		<EmbPoint ID="12" X="271.29177900000002" Y="1.2000000000000028" Z="40" />
		<EmbPoint ID="13" X="271.29177900000002" Y="-1.1999999999999993" Z="40" />
		<EmbPoint ID="14" X="271.29177900000002" Y="-3.6000000000000014" Z="40" />
		<EmbPoint ID="15" X="271.29177900000002" Y="-6" Z="40" />
		<EmbPoint ID="16" X="271.29177900000002" Y="-8.3999999999999986" Z="40" />
		<EmbPoint ID="17" X="271.29177900000002" Y="-10.799999999999997" Z="40" />
		<EmbPoint ID="18" X="271.29177900000002" Y="-13.199999999999996" Z="40" />
		<EmbPoint ID="19" X="271.29177900000002" Y="-15.600000000000001" Z="40" />
		<EmbPoint ID="20" X="271.29177900000002" Y="-18" Z="40" />
		<EmbPoint ID="21" X="271.29177900000002" Y="-20.399999999999999" Z="40" />
		<EmbPoint ID="22" X="271.29177900000002" Y="-22.799999999999997" Z="40" />
		<EmbPoint ID="23" X="271.29177900000002" Y="-25.199999999999996" Z="40" />
		<EmbPoint ID="24" X="271.29177900000002" Y="-27.599999999999994" Z="40" />
		<EmbPoint ID="25" X="271.29177900000002" Y="-30" Z="40" />
		<EmbPoint ID="26" X="271.29177900000002" Y="-30" Z="36.799999999999997" />
		<EmbPoint ID="27" X="271.29177900000002" Y="-30" Z="33.600000000000001" />
		<EmbPoint ID="28" X="271.29177900000002" Y="-30" Z="30.399999999999999" />
		<EmbPoint ID="29" X="271.29177900000002" Y="-30" Z="27.199999999999999" />
		<EmbPoint ID="30" X="271.29177900000002" Y="-30" Z="24" />
		<EmbPoint ID="31" X="271.29177900000002" Y="-30" Z="20.799999999999997" />
		<EmbPoint ID="32" X="271.29177900000002" Y="-30" Z="17.599999999999998" />
		<EmbPoint ID="33" X="271.29177900000002" Y="-30" Z="14.399999999999999" />
		<EmbPoint ID="34" X="271.29177900000002" Y="-30" Z="11.199999999999999" />
		<EmbPoint ID="35" X="271.29177900000002" Y="-30" Z="8" />
		<EmbPoint ID="36" X="271.29177900000002" Y="-30" Z="4.7999999999999972" />
		<EmbPoint ID="37" X="271.29177900000002" Y="-30" Z="1.5999999999999943" />
		<EmbPoint ID="38" X="271.29177900000002" Y="-30" Z="-1.6000000000000014" />
		<EmbPoint ID="39" X="271.29177900000002" Y="-30" Z="-4.8000000000000043" />
		<EmbPoint ID="40" X="271.29177900000002" Y="-30" Z="-8" />
		<EmbPoint ID="41" X="271.29177900000002" Y="-30" Z="-11.200000000000003" />
		<EmbPoint ID="42" X="271.29177900000002" Y="-30" Z="-14.400000000000006" />
		<EmbPoint ID="43" X="271.29177900000002" Y="-30" Z="-17.600000000000001" />
		<EmbPoint ID="44" X="271.29177900000002" Y="-30" Z="-20.800000000000004" />
		<EmbPoint ID="45" X="271.29177900000002" Y="-30" Z="-24" />
		<EmbPoint ID="46" X="271.29177900000002" Y="-30" Z="-27.200000000000003" />
		<EmbPoint ID="47" X="271.29177900000002" Y="-30" Z="-30.400000000000006" />
		<EmbPoint ID="48" X="271.29177900000002" Y="-30" Z="-33.600000000000009" />
		<EmbPoint ID="49" X="271.29177900000002" Y="-30" Z="-36.800000000000011" />
		<EmbPoint ID="50" X="271.29177900000002" Y="-30" Z="-40" />
		<EmbPoint ID="51" X="271.29177900000002" Y="-27.600000000000001" Z="-40" />
		<EmbPoint ID="52" X="271.29177900000002" Y="-25.199999999999999" Z="-40" />
		<EmbPoint ID="53" X="271.29177900000002" Y="-22.800000000000001" Z="-40" />
		<EmbPoint ID="54" X="271.29177900000002" Y="-20.399999999999999" Z="-40" />
		<EmbPoint ID="55" X="271.29177900000002" Y="-18" Z="-40" />
		<EmbPoint ID="56" X="271.29177900000002" Y="-15.600000000000001" Z="-40" />
		<EmbPoint ID="57" X="271.29177900000002" Y="-13.199999999999999" Z="-40" />
		<EmbPoint ID="58" X="271.29177900000002" Y="-10.800000000000001" Z="-40" />
		<EmbPoint ID="59" X="271.29177900000002" Y="-8.4000000000000021" Z="-40" />
		<EmbPoint ID="60" X="271.29177900000002" Y="-6" Z="-40" />
		<EmbPoint ID="61" X="271.29177900000002" Y="-3.6000000000000014" Z="-40" />
		<EmbPoint ID="62" X="271.29177900000002" Y="-1.2000000000000028" Z="-40" />
		<EmbPoint ID="63" X="271.29177900000002" Y="1.1999999999999993" Z="-40" />
		<EmbPoint ID="64" X="271.29177900000002" Y="3.6000000000000014" Z="-40" />
		<EmbPoint ID="65" X="271.29177900000002" Y="6" Z="-40" />
		<EmbPoint ID="66" X="271.29177900000002" Y="8.3999999999999986" Z="-40" />
		<EmbPoint ID="67" X="271.29177900000002" Y="10.799999999999997" Z="-40" />
		<EmbPoint ID="68" X="271.29177900000002" Y="13.199999999999996" Z="-40" />
		<EmbPoint ID="69" X="271.29177900000002" Y="15.600000000000001" Z="-40" />
		<EmbPoint ID="70" X="271.29177900000002" Y="18" Z="-40" />
		<EmbPoint ID="71" X="271.29177900000002" Y="20.399999999999999" Z="-40" />
		<EmbPoint ID="72" X="271.29177900000002" Y="22.799999999999997" Z="-40" />
		<EmbPoint ID="73" X="271.29177900000002" Y="25.199999999999996" Z="-40" />
		<EmbPoint ID="74" X="271.29177900000002" Y="27.599999999999994" Z="-40" />
		<EmbPoint ID="75" X="271.29177900000002" Y="30" Z="-40" />
		<EmbPoint ID="76" X="271.29177900000002" Y="30" Z="-36.799999999999997" />
		<EmbPoint ID="77" X="271.29177900000002" Y="30" Z="-33.600000000000001" />
		<EmbPoint ID="78" X="271.29177900000002" Y="30" Z="-30.399999999999999" />
		<EmbPoint ID="79" X="271.29177900000002" Y="30" Z="-27.199999999999999" />
		<EmbPoint ID="80" X="271.29177900000002" Y="30" Z="-24" />
		<EmbPoint ID="81" X="271.29177900000002" Y="30" Z="-20.799999999999997" />
		<EmbPoint ID="82" X="271.29177900000002" Y="30" Z="-17.599999999999998" />
		<EmbPoint ID="83" X="271.29177900000002" Y="30" Z="-14.399999999999999" />
		<EmbPoint ID="84" X="271.29177900000002" Y="30" Z="-11.199999999999999" />
		<EmbPoint ID="85" X="271.29177900000002" Y="30" Z="-8" />
		<EmbPoint ID="86" X="271.29177900000002" Y="30" Z="-4.7999999999999972" />
		<EmbPoint ID="87" X="271.29177900000002" Y="30" Z="-1.5999999999999943" />
		<EmbPoint ID="88" X="271.29177900000002" Y="30" Z="1.6000000000000014" />
		<EmbPoint ID="89" X="271.29177900000002" Y="30" Z="4.8000000000000043" />
		<EmbPoint ID="90" X="271.29177900000002" Y="30" Z="8" />
		<EmbPoint ID="91" X="271.29177900000002" Y="30" Z="11.200000000000003" />
		<EmbPoint ID="92" X="271.29177900000002" Y="30" Z="14.400000000000006" />
		<EmbPoint ID="93" X="271.29177900000002" Y="30" Z="17.600000000000001" />
		<EmbPoint ID="94" X="271.29177900000002" Y="30" Z="20.800000000000004" />
		<EmbPoint ID="95" X="271.29177900000002" Y="30" Z="24" />
		<EmbPoint ID="96" X="271.29177900000002" Y="30" Z="27.200000000000003" />
		<EmbPoint ID="97" X="271.29177900000002" Y="30" Z="30.400000000000006" />
		<EmbPoint ID="98" X="271.29177900000002" Y="30" Z="33.600000000000009" />
		<EmbPoint ID="99" X="271.29177900000002" Y="30" Z="36.800000000000011" />
	</Section>
	<Section ID="10" SPID="55" IsDeformed="F" IsClosed="T">
		<EmbPoint ID="0" X="298.29342700000001" Y="30" Z="40" />
		<EmbPoint ID="1" X="298.29342700000001" Y="27.600000000000001" Z="40" />
		<EmbPoint ID="2" X="298.29342700000001" Y="25.199999999999999" Z="40" />
		<EmbPoint ID="3" X="298.29342700000001" Y="22.800000000000001" Z="40" />
		<EmbPoint ID="4" X="298.29342700000001" Y="20.399999999999999" Z="40" />
		<EmbPoint ID="5" X="298.29342700000001" Y="18" Z="40" />
		<EmbPoint ID="6" X="298.29342700000001" Y="15.600000000000001" Z="40" />
		<EmbPoint ID="7" X="298.29342700000001" Y="13.199999999999999" Z="40" />
		<EmbPoint ID="8" X="298.29342700000001" Y="10.800000000000001" Z="40" />
		<EmbPoint ID="9" X="298.29342700000001" Y="8.4000000000000021" Z="40" />
		<EmbPoint ID="10" X="298.29342700000001" Y="6" Z="40" />
		<EmbPoint ID="11" X="298.29342700000001" Y="3.6000000000000014" Z="40" />
		<EmbPoint ID="12" X="298.29342700000001" Y="1.2000000000000028" Z="40" />
		<EmbPoint ID="13" X="298.29342700000001" Y="-1.1999999999999993" Z="40" />
		<EmbPoint ID="14" X="298.29342700000001" Y="-3.6000000000000014" Z="40" />
		<EmbPoint ID="15" X="298.29342700000001" Y="-6" Z="40" />
		<EmbPoint ID="16" X="298.29342700000001" Y="-8.3999999999999986" Z="40" />
		<EmbPoint ID="17" X="298.29342700000001" Y="-10.799999999999997" Z="40" />
		<EmbPoint ID="18" X="298.29342700000001" Y="-13.199999999999996" Z="40" />
		<EmbPoint ID="19" X="298.29342700000001" Y="-15.600000000000001" Z="40" />
		<EmbPoint ID="20" X="298.29342700000001" Y="-18" Z="40" />
		<EmbPoint ID="21" X="298.29342700000001" Y="-20.399999999999999" Z="40" />
		<EmbPoint ID="22" X="298.29342700000001" Y="-22.799999999999997" Z="40" />
		<EmbPoint ID="23" X="298.29342700000001" Y="-25.199999999999996" Z="40" />
		<EmbPoint ID="24" X="298.29342700000001" Y="-27.599999999999994" Z="40" />
		<EmbPoint ID="25" X="298.29342700000001" Y="-30" Z="40" />
		<EmbPoint ID="26" X="298.29342700000001" Y="-30" Z="36.799999999999997" />
		<EmbPoint ID="27" X="298.29342700000001" Y="-30" Z="33.600000000000001" />
		<EmbPoint ID="28" X="298.29342700000001" Y="-30" Z="30.399999999999999" />
		<EmbPoint ID="29" X="298.29342700000001" Y="-30" Z="27.199999999999999" />
		<EmbPoint ID="30" X="298.29342700000001" Y="-30" Z="24" />
		<EmbPoint ID="31" X="298.29342700000001" Y="-30" Z="20.799999999999997" />
		<EmbPoint ID="32" X="298.29342700000001" Y="-30" Z="17.599999999999998" />
		<EmbPoint ID="33" X="298.29342700000001" Y="-30" Z="14.399999999999999" />
		<EmbPoint ID="34" X="298.29342700000001" Y="-30" Z="11.199999999999999" />
		<EmbPoint ID="35" X="298.29342700000001" Y="-30" Z="8" />
		<EmbPoint ID="36" X="298.29342700000001" Y="-30" Z="4.7999999999999972" />
		<EmbPoint ID="37" X="298.29342700000001" Y="-30" Z="1.5999999999999943" />
		<EmbPoint ID="38" X="298.29342700000001" Y="-30" Z="-1.6000000000000014" />
		<EmbPoint ID="39" X="298.29342700000001" Y="-30" Z="-4.8000000000000043" />
		<EmbPoint ID="40" X="298.29342700000001" Y="-30" Z="-8" />
		<EmbPoint ID="41" X="298.29342700000001" Y="-30" Z="-11.200000000000003" />
		<EmbPoint ID="42" X="298.29342700000001" Y="-30" Z="-14.400000000000006" />
		<EmbPoint ID="43" X="298.29342700000001" Y="-30" Z="-17.600000000000001" />
		<EmbPoint ID="44" X="298.29342700000001" Y="-30" Z="-20.800000000000004" />
		<EmbPoint ID="45" X="298.29342700000001" Y="-30" Z="-24" />
		<EmbPoint ID="46" X="298.29342700000001" Y="-30" Z="-27.200000000000003" />
		<EmbPoint ID="47" X="298.29342700000001" Y="-30" Z="-30.400000000000006" />
		<EmbPoint ID="48" X="298.29342700000001" Y="-30" Z="-33.600000000000009" />
		<EmbPoint ID="49" X="298.29342700000001" Y="-30" Z="-36.800000000000011" />
		<EmbPoint ID="50" X="298.29342700000001" Y="-30" Z="-40" />
		<EmbPoint ID="51" X="298.29342700000001" Y="-27.600000000000001" Z="-40" />
		<EmbPoint ID="52" X="298.29342700000001" Y="-25.199999999999999" Z="-40" />
		<EmbPoint ID="53" X="298.29342700000001" Y="-22.800000000000001" Z="-40" />
		<EmbPoint ID="54" X="298.29342700000001" Y="-20.399999999999999" Z="-40" />
		<EmbPoint ID="55" X="298.29342700000001" Y="-18" Z="-40" />
		<EmbPoint ID="56" X="298.29342700000001" Y="-15.600000000000001" Z="-40" />
		<EmbPoint ID="57" X="298.29342700000001" Y="-13.199999999999999" Z="-40" />
		<EmbPoint ID="58" X="298.29342700000001" Y="-10.800000000000001" Z="-40" />
		<EmbPoint ID="59" X="298.29342700000001" Y="-8.4000000000000021" Z="-40" />
		<EmbPoint ID="60" X="298.29342700000001" Y="-6" Z="-40" />
		<EmbPoint ID="61" X="298.29342700000001" Y="-3.6000000000000014" Z="-40" />
		<EmbPoint ID="62" X="298.29342700000001" Y="-1.2000000000000028" Z="-40" />
		<EmbPoint ID="63" X="298.29342700000001" Y="1.1999999999999993" Z="-40" />
		<EmbPoint ID="64" X="298.29342700000001" Y="3.6000000000000014" Z="-40" />
		<EmbPoint ID="65" X="298.29342700000001" Y="6" Z="-40" />
		<EmbPoint ID="66" X="298.29342700000001" Y="8.3999999999999986" Z="-40" />
		<EmbPoint ID="67" X="298.29342700000001" Y="10.799999999999997" Z="-40" />
		<EmbPoint ID="68" X="298.29342700000001" Y="13.199999999999996" Z="-40" />
		<EmbPoint ID="69" X="298.29342700000001" Y="15.600000000000001" Z="-40" />
		<EmbPoint ID="70" X="298.29342700000001" Y="18" Z="-40" />
		<EmbPoint ID="71" X="298.29342700000001" Y="20.399999999999999" Z="-40" />
		<EmbPoint ID="72" X="298.29342700000001" Y="22.799999999999997" Z="-40" />
		<EmbPoint ID="73" X="298.29342700000001" Y="25.199999999999996" Z="-40" />
		<EmbPoint ID="74" X="298.29342700000001" Y="27.599999999999994" Z="-40" />
		<EmbPoint ID="75" X="298.29342700000001" Y="30" Z="-40" />
		<EmbPoint ID="76" X="298.29342700000001" Y="30" Z="-36.799999999999997" />
		<EmbPoint ID="77" X="298.29342700000001" Y="30" Z="-33.600000000000001" />
		<EmbPoint ID="78" X="298.29342700000001" Y="30" Z="-30.399999999999999" />
		<EmbPoint ID="79" X="298.29342700000001" Y="30" Z="-27.199999999999999" />
		<EmbPoint ID="80" X="298.29342700000001" Y="30" Z="-24" />
		<EmbPoint ID="81" X="298.29342700000001" Y="30" Z="-20.799999999999997" />
		<EmbPoint ID="82" X="298.29342700000001" Y="30" Z="-17.599999999999998" />
		<EmbPoint ID="83" X="298.29342700000001" Y="30" Z="-14.399999999999999" />
		<EmbPoint ID="84" X="298.29342700000001" Y="30" Z="-11.199999999999999" />
		<EmbPoint ID="85" X="298.29342700000001" Y="30" Z="-8" />
		<EmbPoint ID="86" X="298.29342700000001" Y="30" Z="-4.7999999999999972" />
		<EmbPoint ID="87" X="298.29342700000001" Y="30" Z="-1.5999999999999943" />
		<EmbPoint ID="88" X="298.29342700000001" Y="30" Z="1.6000000000000014" />
		<EmbPoint ID="89" X="298.29342700000001" Y="30" Z="4.8000000000000043" />
		<EmbPoint ID="90" X="298.29342700000001" Y="30" Z="8" />
		<EmbPoint ID="91" X="298.29342700000001" Y="30" Z="11.200000000000003" />
		<EmbPoint ID="92" X="298.29342700000001" Y="30" Z="14.400000000000006" />
		<EmbPoint ID="93" X="298.29342700000001" Y="30" Z="17.600000000000001" />
		<EmbPoint ID="94" X="298.29342700000001" Y="30" Z="20.800000000000004" />
		<EmbPoint ID="95" X="298.29342700000001" Y="30" Z="24" />
		<EmbPoint ID="96" X="298.29342700000001" Y="30" Z="27.200000000000003" />
		<EmbPoint ID="97" X="298.29342700000001" Y="30" Z="30.400000000000006" />
		<EmbPoint ID="98" X="298.29342700000001" Y="30" Z="33.600000000000009" />
		<EmbPoint ID="99" X="298.29342700000001" Y="30" Z="36.800000000000011" />
	</Section>
</DUT_AutoMorpher>
